suin/calculator.py
suin-0.0.1.dist-info/METADATA
suin-0.0.1.dist-info/WHEEL
suin-0.0.1.dist-info/top_level.txt
suin-0.0.1.dist-info/RECORD
