Metadata-Version: 2.1
Name: suin
Version: 0.0.1
Summary: nice calculator
Home-page: https://github.com/suin0985/oss2025-02-1
Download-URL: https://github.com/suin0985/oss2025-02-1
Author: suin0985
Classifier: Programming Language :: Python :: 3
Classifier: License :: OSI Approved :: MIT License
Classifier: Operating System :: OS Independent
